{
    "id": "vianen",
    "name": "Gemeente Vianen",
    "province": "Utrecht",
    "coordinates": {
        "lat": 51.978,
        "lng": 5.091
    },
    "parkingRules": {
        "free": null,
        "paid": {
            "enabled": null,
            "areas": [],
            "rates": null
        },
        "permits": {
            "required": false,
            "types": []
        },
        "restrictions": {
            "timeLimit": null,
            "noParking": []
        },
        "contact": null,
        "motorcycleSpecific": {
            "dedicatedSpots": [],
            "allowedOnSidewalk": null,
            "freeInPaidZones": null,
            "notes": "Er zijn geen gegevens over parkeerregels beschikbaar voor deze gemeente."
        }
    },
    "lastUpdated": null,
    "sources": []
}